pyppl/__init__.py
pyppl/_fsutil.py
pyppl/_job.py
pyppl/_proc.py
pyppl/channel.py
pyppl/config.py
pyppl/console/__init__.py
pyppl/console/clean.py
pyppl/console/list.py
pyppl/console/logo.py
pyppl/console/plugins.py
pyppl/console/profile.py
pyppl/console/status.py
pyppl/exception.py
pyppl/job.py
pyppl/jobmgr.py
pyppl/logger.py
pyppl/plugin.py
pyppl/proc.py
pyppl/procset.py
pyppl/pyppl.py
pyppl/runner.py
pyppl/template.py
pyppl/utils.py
pyppl-3.2.2.dist-info/entry_points.txt
pyppl-3.2.2.dist-info/LICENSE
pyppl-3.2.2.dist-info/WHEEL
pyppl-3.2.2.dist-info/METADATA
pyppl-3.2.2.dist-info/RECORD
