Metadata-Version: 2.1
Name: pyppl
Version: 3.2.2
Summary: A Python PiPeLine framework
Home-page: https://github.com/pwwang/PyPPL
License: MIT
Author: pwwang
Author-email: pwwang@pwwang.com
Requires-Python: >=3.6,<4.0
Classifier: License :: OSI Approved :: MIT License
Classifier: Programming Language :: Python :: 3
Classifier: Programming Language :: Python :: 3.6
Classifier: Programming Language :: Python :: 3.7
Classifier: Programming Language :: Python :: 3.8
Requires-Dist: attr_property
Requires-Dist: attrs (>=19.3,<20.0)
Requires-Dist: cmdy
Requires-Dist: colorama (>=0.4.1,<0.5.0)
Requires-Dist: diot
Requires-Dist: filelock (>=3.0.0,<4.0.0)
Requires-Dist: liquidpy
Requires-Dist: pluggy (<1.0.0)
Requires-Dist: psutil (>=5.6,<6.0)
Requires-Dist: pyparam
Requires-Dist: pyppl_echo
Requires-Dist: pyppl_export
Requires-Dist: pyppl_lock
Requires-Dist: pyppl_rich
Requires-Dist: pyppl_runners
Requires-Dist: pyppl_strict
Requires-Dist: python-simpleconf
Requires-Dist: python-varname
Requires-Dist: toml (>=0.10,<0.11)
Requires-Dist: transitions (>=0.7,<0.8)
Project-URL: Repository, https://github.com/pwwang/PyPPL
